WindowManager/__init__.py
WindowManager-0.0.2.dist-info/LICENSE.txt
WindowManager-0.0.2.dist-info/METADATA
WindowManager-0.0.2.dist-info/WHEEL
WindowManager-0.0.2.dist-info/top_level.txt
WindowManager-0.0.2.dist-info/RECORD
