Metadata-Version: 2.1
Name: WindowManager
Version: 0.0.2
Summary: WindowManager: Simplified window management.
Author: Itamar Katzover
Author-email: itamar43.katzover43@gmail.com
Classifier: Development Status :: 3 - Alpha
Classifier: Programming Language :: Python :: 3
Classifier: License :: OSI Approved :: MIT License
Requires-Python: >=3.10
License-File: LICENSE.txt
